{"rawData":"{"experimentCode":"dual-change","dotCount":200,"dotDifference":15,"difficultyStep":{"start":1,"end":1,"nReversals":2,"current":1,"currentReversals":2},"minimumBlockScore":0.1,"advisorLists":[[{"id":2,"adviceType":4,"styleClass":"advisorChoice-advisor-6","voice":{"basePath":"","id":null,"nameHTML":"","name":"","skipAudioPreload":true,"lines":{"think_left":{"filePath":null,"string":"I think it was on the LEFT","loaded":false,"loading":false,"data":null,"buffer":null,"side":0,"confidence":0},"think_right":{"filePath":null,"string":"I think it was on the RIGHT","loaded":false,"loading":false,"data":null,"buffer":null,"side":1,"confidence":0},"left_think":{"filePath":null,"string":"It was on the LEFT, I think","loaded":false,"loading":false,"data":null,"buffer":null,"side":0,"confidence":0},"right_think":{"filePath":null,"string":"It was on the RIGHT, I think","loaded":false,"loading":false,"data":null,"buffer":null,"side":1,"confidence":0},"intro":{"filePath":null,"string":"Hello, my name is ","loaded":false,"loading":false,"data":null,"buffer":null,"side":null,"confidence":null}}},"portraitId":1,"portraitSrc":"assets/image/comp.jpg","portrait":{},"lastAdvice":null,"practice":false,"groupId":null,"isCue":true,"advisorText":{}},{"id":1,"adviceType":3,"styleClass":"advisorChoice-advisor-5","voice":{"basePath":"","id":null,"nameHTML":"","name":"","skipAudioPreload":true,"lines":{"think_left":{"filePath":null,"string":"I think it was on the LEFT","loaded":false,"loading":false,"data":null,"buffer":null,"side":0,"confidence":0},"think_right":{"filePath":null,"string":"I think it was on the RIGHT","loaded":false,"loading":false,"data":null,"buffer":null,"side":1,"confidence":0},"left_think":{"filePath":null,"string":"It was on the LEFT, I think","loaded":false,"loading":false,"data":null,"buffer":null,"side":0,"confidence":0},"right_think":{"filePath":null,"string":"It was on the RIGHT, I think","loaded":false,"loading":false,"data":null,"buffer":null,"side":1,"confidence":0},"intro":{"filePath":null,"string":"Hello, my name is ","loaded":false,"loading":false,"data":null,"buffer":null,"side":null,"confidence":null}}},"portraitId":4,"portraitSrc":"assets/image/human.jpg","portrait":{},"lastAdvice":null,"practice":false,"groupId":null,"isCue":true,"advisorText":{}}]],"practiceAdvisors":[{"id":1,"adviceType":0,"styleClass":"advisorChoice-advisor-4","voice":{"basePath":"","id":null,"nameHTML":"","name":"","skipAudioPreload":true,"lines":{"think_left":{"filePath":null,"string":"I think it was on the LEFT","loaded":false,"loading":false,"data":null,"buffer":null,"side":0,"confidence":0},"think_right":{"filePath":null,"string":"I think it was on the RIGHT","loaded":false,"loading":false,"data":null,"buffer":null,"side":1,"confidence":0},"left_think":{"filePath":null,"string":"It was on the LEFT, I think","loaded":false,"loading":false,"data":null,"buffer":null,"side":0,"confidence":0},"right_think":{"filePath":null,"string":"It was on the RIGHT, I think","loaded":false,"loading":false,"data":null,"buffer":null,"side":1,"confidence":0},"intro":{"filePath":null,"string":"Hello, my name is ","loaded":false,"loading":false,"data":null,"buffer":null,"side":null,"confidence":null}}},"portraitId":3,"portraitSrc":"assets/image/human.jpg","portrait":{},"lastAdvice":null,"practice":true,"groupId":null,"isCue":true,"advisorText":{}},{"id":2,"adviceType":0,"styleClass":"advisorChoice-advisor-2","voice":{"basePath":"","id":null,"nameHTML":"","name":"","skipAudioPreload":true,"lines":{"think_left":{"filePath":null,"string":"I think it was on the LEFT","loaded":false,"loading":false,"data":null,"buffer":null,"side":0,"confidence":0},"think_right":{"filePath":null,"string":"I think it was on the RIGHT","loaded":false,"loading":false,"data":null,"buffer":null,"side":1,"confidence":0},"left_think":{"filePath":null,"string":"It was on the LEFT, I think","loaded":false,"loading":false,"data":null,"buffer":null,"side":0,"confidence":0},"right_think":{"filePath":null,"string":"It was on the RIGHT, I think","loaded":false,"loading":false,"data":null,"buffer":null,"side":1,"confidence":0},"intro":{"filePath":null,"string":"Hello, my name is ","loaded":false,"loading":false,"data":null,"buffer":null,"side":null,"confidence":null}}},"portraitId":6,"portraitSrc":"assets/image/comp.jpg","portrait":{},"lastAdvice":null,"practice":true,"groupId":null,"isCue":true,"advisorText":{}}],"advisors":[{"id":2,"adviceType":4,"styleClass":"advisorChoice-advisor-6","voice":{"basePath":"","id":null,"nameHTML":"","name":"","skipAudioPreload":true,"lines":{"think_left":{"filePath":null,"string":"I think it was on the LEFT","loaded":false,"loading":false,"data":null,"buffer":null,"side":0,"confidence":0},"think_right":{"filePath":null,"string":"I think it was on the RIGHT","loaded":false,"loading":false,"data":null,"buffer":null,"side":1,"confidence":0},"left_think":{"filePath":null,"string":"It was on the LEFT, I think","loaded":false,"loading":false,"data":null,"buffer":null,"side":0,"confidence":0},"right_think":{"filePath":null,"string":"It was on the RIGHT, I think","loaded":false,"loading":false,"data":null,"buffer":null,"side":1,"confidence":0},"intro":{"filePath":null,"string":"Hello, my name is ","loaded":false,"loading":false,"data":null,"buffer":null,"side":null,"confidence":null}}},"portraitId":1,"portraitSrc":"assets/image/comp.jpg","portrait":{},"lastAdvice":null,"practice":false,"groupId":null,"isCue":true,"advisorText":{}},{"id":1,"adviceType":3,"styleClass":"advisorChoice-advisor-5","voice":{"basePath":"","id":null,"nameHTML":"","name":"","skipAudioPreload":true,"lines":{"think_left":{"filePath":null,"string":"I think it was on the LEFT","loaded":false,"loading":false,"data":null,"buffer":null,"side":0,"confidence":0},"think_right":{"filePath":null,"string":"I think it was on the RIGHT","loaded":false,"loading":false,"data":null,"buffer":null,"side":1,"confidence":0},"left_think":{"filePath":null,"string":"It was on the LEFT, I think","loaded":false,"loading":false,"data":null,"buffer":null,"side":0,"confidence":0},"right_think":{"filePath":null,"string":"It was on the RIGHT, I think","loaded":false,"loading":false,"data":null,"buffer":null,"side":1,"confidence":0},"intro":{"filePath":null,"string":"Hello, my name is ","loaded":false,"loading":false,"data":null,"buffer":null,"side":null,"confidence":null}}},"portraitId":4,"portraitSrc":"assets/image/human.jpg","portrait":{},"lastAdvice":null,"practice":false,"groupId":null,"isCue":true,"advisorText":{}}],"contingentAdvisors":[[],[],[]],"blockStructure":[{"1":2,"2":2},{"1":2,"2":2},{"1":2,"2":2},{"1":2,"2":2},{"1":2,"2":2},{"1":2,"2":2}],"practiceBlockStructure":[{"0":2},{"0":2}],"blk4Structure":[{"5":2}],"preTrialInterval":400,"preStimulusInterval":500,"questionnaireStack":[{"id":2,"adviceType":4,"styleClass":"advisorChoice-advisor-6","voice":{"basePath":"","id":null,"nameHTML":"","name":"","skipAudioPreload":true,"lines":{"think_left":{"filePath":null,"string":"I think it was on the LEFT","loaded":false,"loading":false,"data":null,"buffer":null,"side":0,"confidence":0},"think_right":{"filePath":null,"string":"I think it was on the RIGHT","loaded":false,"loading":false,"data":null,"buffer":null,"side":1,"confidence":0},"left_think":{"filePath":null,"string":"It was on the LEFT, I think","loaded":false,"loading":false,"data":null,"buffer":null,"side":0,"confidence":0},"right_think":{"filePath":null,"string":"It was on the RIGHT, I think","loaded":false,"loading":false,"data":null,"buffer":null,"side":1,"confidence":0},"intro":{"filePath":null,"string":"Hello, my name is ","loaded":false,"loading":false,"data":null,"buffer":null,"side":null,"confidence":null}}},"portraitId":1,"portraitSrc":"assets/image/comp.jpg","portrait":{},"lastAdvice":null,"practice":false,"groupId":null,"isCue":true,"advisorText":{}},{"id":1,"adviceType":3,"styleClass":"advisorChoice-advisor-5","voice":{"basePath":"","id":null,"nameHTML":"","name":"","skipAudioPreload":true,"lines":{"think_left":{"filePath":null,"string":"I think it was on the LEFT","loaded":false,"loading":false,"data":null,"buffer":null,"side":0,"confidence":0},"think_right":{"filePath":null,"string":"I think it was on the RIGHT","loaded":false,"loading":false,"data":null,"buffer":null,"side":1,"confidence":0},"left_think":{"filePath":null,"string":"It was on the LEFT, I think","loaded":false,"loading":false,"data":null,"buffer":null,"side":0,"confidence":0},"right_think":{"filePath":null,"string":"It was on the RIGHT, I think","loaded":false,"loading":false,"data":null,"buffer":null,"side":1,"confidence":0},"intro":{"filePath":null,"string":"Hello, my name is ","loaded":false,"loading":false,"data":null,"buffer":null,"side":null,"confidence":null}}},"portraitId":4,"portraitSrc":"assets/image/human.jpg","portrait":{},"lastAdvice":null,"practice":false,"groupId":null,"isCue":true,"advisorText":{}},{"id":1,"adviceType":3,"styleClass":"advisorChoice-advisor-5","voice":{"basePath":"","id":null,"nameHTML":"","name":"","skipAudioPreload":true,"lines":{"think_left":{"filePath":null,"string":"I think it was on the LEFT","loaded":false,"loading":false,"data":null,"buffer":null,"side":0,"confidence":0},"think_right":{"filePath":null,"string":"I think it was on the RIGHT","loaded":false,"loading":false,"data":null,"buffer":null,"side":1,"confidence":0},"left_think":{"filePath":null,"string":"It was on the LEFT, I think","loaded":false,"loading":false,"data":null,"buffer":null,"side":0,"confidence":0},"right_think":{"filePath":null,"string":"It was on the RIGHT, I think","loaded":false,"loading":false,"data":null,"buffer":null,"side":1,"confidence":0},"intro":{"filePath":null,"string":"Hello, my name is ","loaded":false,"loading":false,"data":null,"buffer":null,"side":null,"confidence":null}}},"portraitId":4,"portraitSrc":"assets/image/human.jpg","portrait":{},"lastAdvice":null,"practice":false,"groupId":null,"isCue":true,"advisorText":{}},{"id":2,"adviceType":4,"styleClass":"advisorChoice-advisor-6","voice":{"basePath":"","id":null,"nameHTML":"","name":"","skipAudioPreload":true,"lines":{"think_left":{"filePath":null,"string":"I think it was on the LEFT","loaded":false,"loading":false,"data":null,"buffer":null,"side":0,"confidence":0},"think_right":{"filePath":null,"string":"I think it was on the RIGHT","loaded":false,"loading":false,"data":null,"buffer":null,"side":1,"confidence":0},"left_think":{"filePath":null,"string":"It was on the LEFT, I think","loaded":false,"loading":false,"data":null,"buffer":null,"side":0,"confidence":0},"right_think":{"filePath":null,"string":"It was on the RIGHT, I think","loaded":false,"loading":false,"data":null,"buffer":null,"side":1,"confidence":0},"intro":{"filePath":null,"string":"Hello, my name is ","loaded":false,"loading":false,"data":null,"buffer":null,"side":null,"confidence":null}}},"portraitId":1,"portraitSrc":"assets/image/comp.jpg","portrait":{},"lastAdvice":null,"practice":false,"groupId":null,"isCue":true,"advisorText":{}}],"stimulusDuration":160,"feedbackDuration":100,"completionURL":"https://app.prolific.ac/submissions/complete?cc=MX5PC2Z4","confidenceOn":false,"beepOn":false,"audioSrc":"assets/audio/beep.mp3","staircase":false,"redirect":"https://app.prolific.co/submissions/complete?cc=595E8D06","CBcondition":2,"advisorClass":"Cue","trials":[{"type":0,"typeName":"catch","block":0,"advisorSet":0,"defaultAdvisor":null,"advisorId":0,"advisor0id":null,"advisor1id":null,"choice":[],"changes":null,"answer":[1,null],"confidence":[20,null],"whichSide":1,"practice":true,"feedback":true,"warnings":[],"stimulusDrawTime":[6846],"stimulusOffTime":[1062],"fixationDrawTime":[6346],"advisorAnswer":null,"advisorCorrect":null,"advisorConfidence":0,"leftGrid":null,"rightGrid":null,"whereLarger":null,"trialSelect":null,"id":1,"confidenceCategory":null,"advice":null,"advisor0advice":null,"advisor1advice":null,"advisorAgrees":null,"advisor0agrees":null,"advisor1agrees":null,"dotDifference":15,"grid":{"dotCountL":185,"dotCountR":215,"forcedTrials":[13,5,7,86,116,114,20,59,80,1,11,22,35,15,92,69,96,70,113,40,21,111,71,107,102,82,50,9,112,101,74,47,99,58,17,68,16,26,97,18,83,104,93,77,28,23,12,48,91,45,51,54,75,24,115,31,38,14,78,117,0,67,57,4,46,55,60,49,119,62,52,84,65,73,25,103,39,6,98,90,106,44,63,34,105,76,36,108,30,37,27,19,89,3,43,53,41,66,118,110,81,109,95,87,85,79,88,2,42,10,32,100,33,64,56,94,72,8,29,61],"choiceTrials":[3,70,170,236,30,61,217,28,204,142,62,78,27,52,184,138,88,18,83,46,179,134,100,136,112,117,211,195,82,123,104,116,235,238,109,224,92,148,147,149,196,108,197,72,65,210,64,125,7,154,29,225,228,137,0,50,214,17,166,201,114,105,91,13,59,103,221,181,226,120,31,113,194,1,32,24,87,124,180,173,145,203,63,144,155,237,95,209,45,239,218,102,141,58,111,90,191,10,167,66,205,33,220,34,67,49,164,107,176,106,5,160,19,129,206,130,143,89,172,25,56,26,171,189,42,159,233,227,182,86,230,110,48,22,2,11,158,115,161,73,57,140,219,175,93,223,119,132,231,183,68,16,12,8,38,131,43,14,126,23,54,157,190,4,192,193,37,75,163,139,212,168,40,71,169,187,60,98,39,21,101,94,55,165,222,156,79,150,121,199,127,122,151,69,96,215,85,41,185,128,51,47,202,178,15,84,208,80,188,6,53,186,216,81,213,99,162,234,153,97,77,76,232,177,152,198,20,135,118,174,229,44,74,9,200,207,133,35,146,36],"blk4Trials":[43,9,21,19,34,17,16,10,13,35,31,44,40,51,53,6,39,58,49,15,45,59,32,57,38,24,42,56,14,0,47,12,2,20,36,54,41,25,26,1,22,7,23,18,11,27,52,33,4,46,55,29,30,48,28,5,8,3,37,50],"currentTrialType":0,"gridWidth":20,"gridHeight":20,"dotWidth":3,"dotHeight":3,"paddingX":6,"paddingY":6,"gridL":[[1,0,1,1,1,1,1,0,1,0,1,0,1,1,0,1,1,1,0,1],[0,1,1,0,1,0,0,0,0,0,1,0,0,1,1,1,0,1,1,0],[1,1,0,1,1,0,0,0,1,0,0,1,0,0,0,0,0,0,1,0],[0,0,1,0,1,0,1,0,0,1,0,0,0,0,1,0,0,1,1,1],[1,1,0,0,1,1,0,0,0,1,0,1,0,0,1,0,1,1,0,1],[1,1,0,0,1,1,0,0,0,1,0,0,1,1,0,1,1,1,1,0],[0,1,1,1,0,0,0,0,1,1,0,0,0,1,0,0,0,0,0,0],[0,1,0,0,0,1,0,1,0,1,1,1,0,1,1,0,0,0,1,0],[1,1,1,1,1,1,0,0,1,0,1,0,0,0,0,1,1,1,0,0],[0,0,1,0,0,0,0,1,0,1,1,0,0,0,0,1,1,1,0,0],[0,1,1,1,0,0,0,0,0,0,0,1,1,1,0,1,0,0,0,1],[0,1,0,1,0,0,1,1,1,1,1,1,0,0,0,0,1,1,1,1],[0,0,1,0,0,0,0,0,1,1,1,1,0,0,1,0,0,1,1,1],[0,0,1,0,0,1,1,1,0,1,0,0,1,1,1,0,1,0,1,0],[1,0,1,1,1,0,0,1,1,1,1,1,0,0,1,0,1,1,1,1],[0,0,0,0,0,0,0,0,1,1,0,1,1,0,0,0,1,0,0,0],[1,1,1,0,0,1,0,0,1,1,0,0,0,0,0,1,1,0,1,0],[1,0,0,0,1,0,0,0,0,0,1,0,1,1,1,0,1,1,1,0],[0,0,0,1,0,1,0,1,1,0,1,1,0,0,0,0,1,0,1,1],[1,1,0,1,1,0,0,1,0,0,0,0,0,0,1,0,1,0,1,0]],"gridR":[[1,1,0,1,1,1,1,1,1,0,1,1,1,1,1,0,0,0,1,0],[0,0,0,1,1,1,1,1,1,0,1,1,1,1,0,0,0,1,0,1],[1,1,0,1,1,1,1,1,0,1,0,1,0,1,1,0,0,1,0,0],[0,0,1,1,0,0,1,0,0,0,0,0,0,0,1,0,1,1,0,1],[0,0,1,0,0,1,1,0,1,0,0,0,0,0,0,1,0,1,1,1],[0,1,1,0,1,1,1,0,1,1,1,1,0,0,0,1,0,0,1,1],[1,0,0,1,0,1,1,0,0,0,0,0,0,0,0,1,1,1,0,1],[1,1,1,1,1,0,1,0,0,0,0,0,1,0,1,0,0,0,1,0],[0,1,0,1,1,1,1,0,1,1,0,0,0,0,0,0,1,0,0,1],[0,0,0,0,0,1,0,1,1,1,0,0,1,0,1,1,1,0,1,1],[1,0,1,0,1,0,0,1,0,1,1,1,0,1,1,0,1,1,1,1],[1,1,1,0,0,1,1,0,1,1,1,1,1,0,0,1,0,0,0,0],[1,1,1,1,1,0,0,1,0,0,1,0,1,0,1,0,0,1,1,1],[0,1,1,1,0,0,0,0,1,1,1,0,1,1,1,1,1,1,0,0],[0,1,1,0,1,1,0,0,1,0,0,0,0,1,0,0,1,0,0,1],[1,1,1,0,0,0,1,1,0,1,1,0,1,1,0,1,1,1,1,1],[0,0,1,1,0,0,1,0,0,0,0,1,1,1,1,1,1,0,1,1],[0,1,1,0,0,1,1,0,0,1,1,1,0,0,1,1,1,1,0,0],[1,1,0,1,0,1,1,1,1,1,0,1,1,0,1,0,0,1,0,0],[0,1,0,1,0,1,0,0,1,0,0,1,1,0,1,1,1,0,1,0]],"displayWidth":192,"displayHeight":192,"spacing":100,"style":{"gridBorderColor":"#ffffff","gridBorderWidth":"3","dotColor":"#ffffff","backgroundColor":"rgb(163, 163, 163)","dotLineWidth":"1"}},"pluginResponse":[{"startTime":5944,"rt":2069,"response":[{"id":0,"name":"answer","answer":"70","prompt":"<p>Left click on the slider, click Continue to confirm.</p>","lastChangedTime":7669.000000000001}],"stimulusOffTime":1062,"trial_type":"canvas-sliders-response","trial_index":3,"time_elapsed":6839,"internal_node_id":"0.0-3.0-0.0"}],"stimulusParent":null,"repeatRejection":null,"points":91},{"type":0,"typeName":"catch","block":0,"advisorSet":0,"defaultAdvisor":null,"advisorId":0,"advisor0id":null,"advisor1id":null,"choice":[],"changes":null,"answer":[0,null],"confidence":[10,null],"whichSide":0,"practice":true,"feedback":true,"warnings":[],"stimulusDrawTime":[9619],"stimulusOffTime":[1063],"fixationDrawTime":[9119],"advisorAnswer":null,"advisorCorrect":null,"advisorConfidence":0,"leftGrid":null,"rightGrid":null,"whereLarger":null,"trialSelect":null,"id":2,"confidenceCategory":null,"advice":null,"advisor0advice":null,"advisor1advice":null,"advisorAgrees":null,"advisor0agrees":null,"advisor1agrees":null,"dotDifference":15,"grid":{"dotCountL":215,"dotCountR":185,"forcedTrials":[13,5,7,86,116,114,20,59,80,1,11,22,35,15,92,69,96,70,113,40,21,111,71,107,102,82,50,9,112,101,74,47,99,58,17,68,16,26,97,18,83,104,93,77,28,23,12,48,91,45,51,54,75,24,115,31,38,14,78,117,0,67,57,4,46,55,60,49,119,62,52,84,65,73,25,103,39,6,98,90,106,44,63,34,105,76,36,108,30,37,27,19,89,3,43,53,41,66,118,110,81,109,95,87,85,79,88,2,42,10,32,100,33,64,56,94,72,8,29,61],"choiceTrials":[3,70,170,236,30,61,217,28,204,142,62,78,27,52,184,138,88,18,83,46,179,134,100,136,112,117,211,195,82,123,104,116,235,238,109,224,92,148,147,149,196,108,197,72,65,210,64,125,7,154,29,225,228,137,0,50,214,17,166,201,114,105,91,13,59,103,221,181,226,120,31,113,194,1,32,24,87,124,180,173,145,203,63,144,155,237,95,209,45,239,218,102,141,58,111,90,191,10,167,66,205,33,220,34,67,49,164,107,176,106,5,160,19,129,206,130,143,89,172,25,56,26,171,189,42,159,233,227,182,86,230,110,48,22,2,11,158,115,161,73,57,140,219,175,93,223,119,132,231,183,68,16,12,8,38,131,43,14,126,23,54,157,190,4,192,193,37,75,163,139,212,168,40,71,169,187,60,98,39,21,101,94,55,165,222,156,79,150,121,199,127,122,151,69,96,215,85,41,185,128,51,47,202,178,15,84,208,80,188,6,53,186,216,81,213,99,162,234,153,97,77,76,232,177,152,198,20,135,118,174,229,44,74,9,200,207,133,35,146,36],"blk4Trials":[43,9,21,19,34,17,16,10,13,35,31,44,40,51,53,6,39,58,49,15,45,59,32,57,38,24,42,56,14,0,47,12,2,20,36,54,41,25,26,1,22,7,23,18,11,27,52,33,4,46,55,29,30,48,28,5,8,3,37,50],"currentTrialType":0,"gridWidth":20,"gridHeight":20,"dotWidth":3,"dotHeight":3,"paddingX":6,"paddingY":6,"gridL":[[1,0,1,1,1,1,1,1,1,1,1,0,1,0,0,1,0,1,1,0],[0,0,0,0,0,1,1,0,1,1,1,0,0,0,0,1,0,0,1,0],[1,1,1,1,1,1,1,0,1,0,0,0,1,0,1,1,1,0,1,1],[1,1,1,0,0,1,0,1,1,1,1,1,1,1,0,1,1,0,0,0],[1,1,0,0,1,0,0,1,1,0,1,0,1,0,0,1,1,1,0,1],[0,0,1,0,0,0,1,0,1,1,0,0,1,1,1,1,1,0,1,1],[1,0,0,1,0,0,1,1,1,1,1,0,0,1,1,1,1,1,1,0],[1,1,0,0,0,0,0,1,0,0,1,1,1,0,1,1,1,0,0,1],[1,1,1,1,1,1,1,0,1,0,0,1,0,1,1,1,1,1,0,0],[0,1,1,0,0,0,1,0,1,1,1,0,0,0,1,0,0,1,0,0],[1,0,1,0,0,0,1,0,0,0,0,0,0,1,1,1,1,1,1,1],[0,1,1,1,1,1,0,0,1,1,1,0,1,1,1,1,1,0,0,1],[1,1,1,0,0,0,0,0,1,0,1,1,0,0,1,0,1,1,0,1],[1,1,1,0,0,1,0,1,0,1,1,0,1,0,1,1,1,0,0,1],[0,0,0,1,1,0,1,0,1,0,0,1,1,0,0,0,0,0,0,0],[0,1,0,1,0,1,1,0,0,1,0,1,1,1,0,1,0,1,0,0],[1,1,1,0,1,1,0,1,1,1,1,0,1,0,1,1,0,0,0,1],[1,0,1,0,1,0,0,0,0,1,0,1,0,1,0,0,0,0,0,1],[1,1,1,0,0,0,0,1,0,0,1,1,0,1,0,0,1,0,0,1],[0,0,1,0,1,0,1,1,1,1,1,0,0,0,0,0,0,1,1,0]],"gridR":[[1,1,0,1,1,1,0,0,1,1,1,0,1,1,0,0,0,0,1,0],[0,1,1,1,1,0,0,0,1,0,0,0,0,0,0,1,1,1,0,1],[0,1,1,0,0,0,1,0,0,0,1,0,0,0,0,1,1,1,0,1],[1,0,1,0,0,0,1,0,0,0,1,0,0,1,1,1,0,1,0,0],[0,1,1,0,0,0,1,1,0,1,0,0,1,0,0,0,1,0,0,1],[0,1,1,0,0,1,1,1,1,0,0,1,1,0,0,0,0,0,1,0],[1,1,1,0,1,0,1,1,1,1,0,0,1,0,0,1,0,1,0,0],[1,1,1,0,0,1,0,1,1,0,1,0,1,0,0,1,1,0,1,0],[0,0,0,1,1,0,1,0,1,0,1,0,1,0,0,1,1,1,0,0],[1,0,1,1,1,1,1,0,1,1,0,0,0,1,1,0,1,1,1,0],[0,0,0,1,0,1,1,1,1,0,1,0,1,0,0,1,1,1,1,0],[0,0,0,1,1,1,0,0,0,0,0,0,1,1,1,0,0,0,0,0],[1,0,0,0,0,1,0,0,0,0,0,0,1,1,0,0,0,1,0,1],[0,0,1,1,0,1,1,0,1,1,0,1,0,1,1,1,1,0,1,0],[1,0,0,1,1,1,1,1,0,1,1,1,0,1,0,0,0,0,1,0],[0,1,1,1,0,0,1,0,0,0,0,0,0,1,0,1,0,0,1,1],[0,1,0,0,0,1,0,1,0,1,1,0,1,0,1,1,1,1,0,0],[0,0,0,1,0,1,0,1,0,0,0,0,1,0,1,1,1,0,0,0],[1,0,0,0,1,0,0,0,0,0,0,0,1,1,0,0,1,1,0,0],[1,1,1,0,0,0,1,0,1,0,1,1,1,0,1,1,1,0,0,0]],"displayWidth":192,"displayHeight":192,"spacing":100,"style":{"gridBorderColor":"#ffffff","gridBorderWidth":"3","dotColor":"#ffffff","backgroundColor":"rgb(163, 163, 163)","dotLineWidth":"1"}},"pluginResponse":[{"startTime":8717,"rt":1864,"response":[{"id":0,"name":"answer","answer":"40","prompt":"<p>Left click on the slider, click Continue to confirm.</p>","lastChangedTime":10245.000000000002}],"stimulusOffTime":1063,"trial_type":"canvas-sliders-response","trial_index":4,"time_elapsed":9407,"internal_node_id":"0.0-4.0-0.0"}],"stimulusParent":null,"repeatRejection":null,"points":175},{"type":0,"typeName":"catch","block":1,"advisorSet":0,"defaultAdvisor":null,"advisorId":0,"advisor0id":null,"advisor1id":null,"choice":[],"changes":null,"answer":[null,null],"confidence":[null,null],"whichSide":1,"practice":true,"feedback":true,"warnings":[],"stimulusDrawTime":[],"stimulusOffTime":[],"fixationDrawTime":[],"advisorAnswer":null,"advisorCorrect":null,"advisorConfidence":0,"leftGrid":null,"rightGrid":null,"whereLarger":null,"trialSelect":null,"id":3,"confidenceCategory":null,"advice":null,"advisor0advice":null,"advisor1advice":null,"advisorAgrees":null,"advisor0agrees":null,"advisor1agrees":null,"dotDifference":null,"grid":null,"pluginResponse":[],"stimulusParent":null,"repeatRejection":null,"points":null},{"type":0,"typeName":"catch","block":1,"advisorSet":0,"defaultAdvisor":null,"advisorId":0,"advisor0id":null,"advisor1id":null,"choice":[],"changes":null,"answer":[null,null],"confidence":[null,null],"whichSide":1,"practice":true,"feedback":true,"warnings":[],"stimulusDrawTime":[],"stimulusOffTime":[],"fixationDrawTime":[],"advisorAnswer":null,"advisorCorrect":null,"advisorConfidence":0,"leftGrid":null,"rightGrid":null,"whereLarger":null,"trialSelect":null,"id":4,"confidenceCategory":null,"advice":null,"advisor0advice":null,"advisor1advice":null,"advisorAgrees":null,"advisor0agrees":null,"advisor1agrees":null,"dotDifference":null,"grid":null,"pluginResponse":[],"stimulusParent":null,"repeatRejection":null,"points":null}],"miscTrials":[{"view_history":"[{\"page_index\":0,\"viewing_time\":517}]","rt":518,"trial_type":"instructions","trial_index":0,"time_elapsed":519,"internal_node_id":"0.0-0.0"},{"view_history":"[{\"page_index\":0,\"viewing_time\":1383},{\"page_index\":1,\"viewing_time\":136},{\"page_index\":2,\"viewing_time\":136},{\"page_index\":3,\"viewing_time\":312},{\"page_index\":4,\"viewing_time\":128},{\"page_index\":5,\"viewing_time\":136},{\"page_index\":6,\"viewing_time\":136},{\"page_index\":7,\"viewing_time\":256},{\"page_index\":8,\"viewing_time\":376},{\"page_index\":9,\"viewing_time\":136},{\"page_index\":10,\"viewing_time\":144},{\"page_index\":11,\"viewing_time\":408}]","rt":3688,"trial_type":"instructions","trial_index":2,"time_elapsed":4767,"internal_node_id":"0.0-2.0"}],"currentTrialIndex":2,"timeStart":1596068135001,"blockCount":null,"numOfTrials":30,"workingMemoryStack":[],"maintainMemoryString":"","totalReward":0,"dotReward":0,"estimateReward":0,"estimateErr":[],"meanEstimateErr":[],"dotsComplete":0,"estimates":[],"radio":[],"generalisedTrustQuestionnaire":null,"changeTime":1500,"maxDD":15,"forcedTrials":[13,5,7,86,116,114,20,59,80,1,11,22,35,15,92,69,96,70,113,40,21,111,71,107,102,82,50,9,112,101,74,47,99,58,17,68,16,26,97,18,83,104,93,77,28,23,12,48,91,45,51,54,75,24,115,31,38,14,78,117,0,67,57,4,46,55,60,49,119,62,52,84,65,73,25,103,39,6,98,90,106,44,63,34,105,76,36,108,30,37,27,19,89,3,43,53,41,66,118,110,81,109,95,87,85,79,88,2,42,10,32,100,33,64,56,94,72,8,29,61],"choiceTrials":[3,70,170,236,30,61,217,28,204,142,62,78,27,52,184,138,88,18,83,46,179,134,100,136,112,117,211,195,82,123,104,116,235,238,109,224,92,148,147,149,196,108,197,72,65,210,64,125,7,154,29,225,228,137,0,50,214,17,166,201,114,105,91,13,59,103,221,181,226,120,31,113,194,1,32,24,87,124,180,173,145,203,63,144,155,237,95,209,45,239,218,102,141,58,111,90,191,10,167,66,205,33,220,34,67,49,164,107,176,106,5,160,19,129,206,130,143,89,172,25,56,26,171,189,42,159,233,227,182,86,230,110,48,22,2,11,158,115,161,73,57,140,219,175,93,223,119,132,231,183,68,16,12,8,38,131,43,14,126,23,54,157,190,4,192,193,37,75,163,139,212,168,40,71,169,187,60,98,39,21,101,94,55,165,222,156,79,150,121,199,127,122,151,69,96,215,85,41,185,128,51,47,202,178,15,84,208,80,188,6,53,186,216,81,213,99,162,234,153,97,77,76,232,177,152,198,20,135,118,174,229,44,74,9,200,207,133,35,146,36],"blk4Trials":[43,9,21,19,34,17,16,10,13,35,31,44,40,51,53,6,39,58,49,15,45,59,32,57,38,24,42,56,14,0,47,12,2,20,36,54,41,25,26,1,22,7,23,18,11,27,52,33,4,46,55,29,30,48,28,5,8,3,37,50],"firstForced":0,"firstChoice":0,"participantId":"HEYLOOKIMANID"}","processedData":"{"id":"HEYLOOKIMANID","groupId":null,"blockCount":null,"catchPerBlock":{"1":2,"2":2},"forcePerBlock":{"1":2,"2":2},"choicePerBlock":{"1":2,"2":2},"practiceCatchPerBlock":{"0":2},"practiceForcePerBlock":{"0":2},"difficultyStep":{"start":1,"end":1,"nReversals":2,"current":1,"currentReversals":2},"dotCount":200,"preTrialInterval":400,"preStimulusInterval":500,"stimulusDuration":160,"feedbackDuration":100,"changeDuration":1500,"timeStart":1596068135001,"experimentDuration":null,"advisors":[{"participantId":"HEYLOOKIMANID","id":2,"adviceType":4,"name":"","portraitSrc":"assets/image/comp.jpg","voiceId":null,"styleClass":"advisorChoice-advisor-6","advisorClass":"Cue","groupId":null},{"participantId":"HEYLOOKIMANID","id":1,"adviceType":3,"name":"","portraitSrc":"assets/image/human.jpg","voiceId":null,"styleClass":"advisorChoice-advisor-5","advisorClass":"Cue","groupId":null},{"participantId":"HEYLOOKIMANID","id":1,"adviceType":0,"name":"","portraitSrc":"assets/image/human.jpg","voiceId":null,"styleClass":"advisorChoice-advisor-4","advisorClass":"Cue","groupId":null},{"participantId":"HEYLOOKIMANID","id":2,"adviceType":0,"name":"","portraitSrc":"assets/image/comp.jpg","voiceId":null,"styleClass":"advisorChoice-advisor-2","advisorClass":"Cue","groupId":null}],"questionnaires":[],"trials":[{"participantId":"HEYLOOKIMANID","id":1,"block":0,"practice":true,"type":0,"typeName":"catch","dotDifference":15,"correctAnswer":1,"initialAnswer":1,"finalAnswer":null,"initialConfidence":20,"finalConfidence":null,"confidenceCategory":null,"advisorAnswer":null,"advisorCorrect":null,"advisorConfidence":0,"whereLarger":null,"leftGrid":null,"rightGrid":null,"trialSelect":null,"hasChoice":false,"choice0":null,"choice1":null,"advisorId":0,"advisorAgrees":null,"adviceSide":null,"adviceString":null,"advisor0id":null,"advisor0adviceSide":null,"advisor0agrees":null,"advisor0adviceString":null,"advisor1id":null,"advisor1adviceSide":null,"advisor1agrees":null,"advisor1adviceString":null,"defaultAdvisor":null,"feedback":true,"grid":"7e785a8bdc0389689e5285d095eda247ce6204df","stimulusParent":null,"repeatRejection":null,"warnings":"","timeInitialStart":5944,"timeInitialFixation":6346,"timeInitialStimOn":6846,"timeInitialStimOff":7006,"timeInitialResponse":8013},{"participantId":"HEYLOOKIMANID","id":2,"block":0,"practice":true,"type":0,"typeName":"catch","dotDifference":15,"correctAnswer":0,"initialAnswer":0,"finalAnswer":null,"initialConfidence":10,"finalConfidence":null,"confidenceCategory":null,"advisorAnswer":null,"advisorCorrect":null,"advisorConfidence":0,"whereLarger":null,"leftGrid":null,"rightGrid":null,"trialSelect":null,"hasChoice":false,"choice0":null,"choice1":null,"advisorId":0,"advisorAgrees":null,"adviceSide":null,"adviceString":null,"advisor0id":null,"advisor0adviceSide":null,"advisor0agrees":null,"advisor0adviceString":null,"advisor1id":null,"advisor1adviceSide":null,"advisor1agrees":null,"advisor1adviceString":null,"defaultAdvisor":null,"feedback":true,"grid":"801caeb7c21455bc65fc9e8f9f4180280990ca3b","stimulusParent":null,"repeatRejection":null,"warnings":"","timeInitialStart":8717,"timeInitialFixation":9119,"timeInitialStimOn":9619,"timeInitialStimOff":9780,"timeInitialResponse":10581},{"participantId":"HEYLOOKIMANID","id":3,"block":1,"practice":true,"type":0,"typeName":"catch","dotDifference":null,"correctAnswer":1,"initialAnswer":null,"finalAnswer":null,"initialConfidence":null,"finalConfidence":null,"confidenceCategory":null,"advisorAnswer":null,"advisorCorrect":null,"advisorConfidence":0,"whereLarger":null,"leftGrid":null,"rightGrid":null,"trialSelect":null,"hasChoice":false,"choice0":null,"choice1":null,"advisorId":0,"advisorAgrees":null,"adviceSide":null,"adviceString":null,"advisor0id":null,"advisor0adviceSide":null,"advisor0agrees":null,"advisor0adviceString":null,"advisor1id":null,"advisor1adviceSide":null,"advisor1agrees":null,"advisor1adviceString":null,"defaultAdvisor":null,"feedback":true,"grid":"2be88ca4242c76e8253ac62474851065032d6833","stimulusParent":null,"repeatRejection":null,"warnings":""},{"participantId":"HEYLOOKIMANID","id":4,"block":1,"practice":true,"type":0,"typeName":"catch","dotDifference":null,"correctAnswer":1,"initialAnswer":null,"finalAnswer":null,"initialConfidence":null,"finalConfidence":null,"confidenceCategory":null,"advisorAnswer":null,"advisorCorrect":null,"advisorConfidence":0,"whereLarger":null,"leftGrid":null,"rightGrid":null,"trialSelect":null,"hasChoice":false,"choice0":null,"choice1":null,"advisorId":0,"advisorAgrees":null,"adviceSide":null,"adviceString":null,"advisor0id":null,"advisor0adviceSide":null,"advisor0agrees":null,"advisor0adviceString":null,"advisor1id":null,"advisor1adviceSide":null,"advisor1agrees":null,"advisor1adviceString":null,"defaultAdvisor":null,"feedback":true,"grid":"2be88ca4242c76e8253ac62474851065032d6833","stimulusParent":null,"repeatRejection":null,"warnings":""}],"debrief":[],"debriefRepQuiz":[]}"}